gitlab_analyzer/__init__.py
gitlab_analyzer/version.py
gitlab_analyzer/analysis/__init__.py
gitlab_analyzer/analysis/error_model.py
gitlab_analyzer/analysis/root_cause_analyzer.py
gitlab_analyzer/analysis/summarizer.py
gitlab_analyzer/api/__init__.py
gitlab_analyzer/api/client.py
gitlab_analyzer/cache/auto_cleanup.py
gitlab_analyzer/cache/mcp_cache.py
gitlab_analyzer/cache/models.py
gitlab_analyzer/core/analysis.py
gitlab_analyzer/core/pipeline_info.py
gitlab_analyzer/mcp/__init__.py
gitlab_analyzer/mcp/server.py
gitlab_analyzer/mcp/formatters/__init__.py
gitlab_analyzer/mcp/formatters/base_formatter.py
gitlab_analyzer/mcp/prompts/__init__.py
gitlab_analyzer/mcp/prompts/advanced.py
gitlab_analyzer/mcp/prompts/debugging.py
gitlab_analyzer/mcp/prompts/educational.py
gitlab_analyzer/mcp/prompts/investigation.py
gitlab_analyzer/mcp/prompts/performance.py
gitlab_analyzer/mcp/resources/__init__.py
gitlab_analyzer/mcp/resources/analysis.py
gitlab_analyzer/mcp/resources/error.py
gitlab_analyzer/mcp/resources/file.py
gitlab_analyzer/mcp/resources/job.py
gitlab_analyzer/mcp/resources/merge_request.py
gitlab_analyzer/mcp/resources/pipeline.py
gitlab_analyzer/mcp/resources/utils.py
gitlab_analyzer/mcp/servers/__init__.py
gitlab_analyzer/mcp/servers/http_server.py
gitlab_analyzer/mcp/servers/server.py
gitlab_analyzer/mcp/servers/sse_server.py
gitlab_analyzer/mcp/services/__init__.py
gitlab_analyzer/mcp/services/error_analysis_service.py
gitlab_analyzer/mcp/services/error_service.py
gitlab_analyzer/mcp/services/file_analysis_service.py
gitlab_analyzer/mcp/services/file_service.py
gitlab_analyzer/mcp/tools/__init__.py
gitlab_analyzer/mcp/tools/cache_tools.py
gitlab_analyzer/mcp/tools/clean_trace_tools.py
gitlab_analyzer/mcp/tools/failed_pipeline_analysis.py
gitlab_analyzer/mcp/tools/job_analysis_tools.py
gitlab_analyzer/mcp/tools/resource_access_tools.py
gitlab_analyzer/mcp/tools/search_tools.py
gitlab_analyzer/mcp/tools/trace_analysis_tools.py
gitlab_pipeline_analyzer-0.13.0.dist-info/licenses/LICENSE
gitlab_pipeline_analyzer-0.13.0.dist-info/METADATA
gitlab_pipeline_analyzer-0.13.0.dist-info/WHEEL
gitlab_pipeline_analyzer-0.13.0.dist-info/entry_points.txt
gitlab_pipeline_analyzer-0.13.0.dist-info/top_level.txt
gitlab_pipeline_analyzer-0.13.0.dist-info/RECORD
