Metadata-Version: 2.4
Name: gitlab-pipeline-analyzer
Version: 0.13.0
Summary: FastMCP server for analyzing GitLab CI/CD pipeline failures
Author-email: Siarhei Skuratovich <sOraCool@gmail.com>
License-Expression: MIT
Keywords: gitlab,ci/cd,pipeline,analysis,mcp,fastmcp
Classifier: Development Status :: 4 - Beta
Classifier: Intended Audience :: Developers
Classifier: Programming Language :: Python :: 3
Classifier: Programming Language :: Python :: 3.10
Classifier: Programming Language :: Python :: 3.11
Classifier: Programming Language :: Python :: 3.12
Classifier: Topic :: Software Development :: Libraries :: Python Modules
Classifier: Topic :: System :: Monitoring
Requires-Python: >=3.10
License-File: LICENSE
Requires-Dist: fastmcp>=2.11.1
Requires-Dist: python-gitlab>=6.2.0
Requires-Dist: httpx>=0.28.1
Requires-Dist: pydantic>=2.11.7
Requires-Dist: typing-extensions>=4.14.1
Requires-Dist: aiosqlite>=0.20.0
Provides-Extra: dev
Requires-Dist: pytest>=8.4.1; extra == "dev"
Requires-Dist: pytest-asyncio>=1.1.0; extra == "dev"
Requires-Dist: pytest-cov>=6.2.1; extra == "dev"
Requires-Dist: ruff>=0.12.7; extra == "dev"
Requires-Dist: mypy>=1.17.1; extra == "dev"
Requires-Dist: tox>=4.28.4; extra == "dev"
Requires-Dist: bandit[toml]>=1.8.6; extra == "dev"
Requires-Dist: pre-commit>=4.2.0; extra == "dev"
Requires-Dist: build>=1.3.0; extra == "dev"
Requires-Dist: twine>=6.1.0; extra == "dev"
Requires-Dist: types-requests>=2.32.4.20250611; extra == "dev"
Provides-Extra: docs
Requires-Dist: sphinx>=7.1.0; extra == "docs"
Requires-Dist: sphinx-rtd-theme>=2.0.0; extra == "docs"
Requires-Dist: myst-parser>=2.0.0; extra == "docs"
Requires-Dist: sphinx-autobuild>=2021.3.14; extra == "docs"
Requires-Dist: sphinxcontrib-mermaid>=0.9.2; extra == "docs"
Dynamic: license-file
